docs/__init__.py
docs/conf.py
docs/settings.py
mattermost_bot/__init__.py
mattermost_bot/bot.py
mattermost_bot/cli.py
mattermost_bot/dispatcher.py
mattermost_bot/mattermost.py
mattermost_bot/settings.py
mattermost_bot/utils.py
mattermost_bot/plugins/__init__.py
mattermost_bot/plugins/access.py
mattermost_bot/plugins/busy.py
mattermost_bot/plugins/hello.py
mattermost_bot/plugins/help.py
mattermost_bot/plugins/info.py
mattermost_bot/plugins/ping.py
mattermost_bot/plugins/sleep.py
mattermost_bot-1.0.20.dist-info/DESCRIPTION.rst
mattermost_bot-1.0.20.dist-info/METADATA
mattermost_bot-1.0.20.dist-info/RECORD
mattermost_bot-1.0.20.dist-info/WHEEL
mattermost_bot-1.0.20.dist-info/entry_points.txt
mattermost_bot-1.0.20.dist-info/metadata.json
mattermost_bot-1.0.20.dist-info/top_level.txt
