Metadata-Version: 2.0
Name: mattermost-bot
Version: 1.0.20
Summary: Simple bot for MatterMost
Home-page: http://github.com/LPgenerator/mattermost_bot
Author: GoTLiuM InSPiRiT
Author-email: gotlium@gmail.com
License: MIT
Keywords: chat bot mattermost
Platform: Any
Classifier: Development Status :: 5 - Production/Stable
Classifier: License :: OSI Approved :: GNU General Public License (GPL)
Classifier: Intended Audience :: Developers
Classifier: Operating System :: OS Independent
Classifier: Programming Language :: Python
Classifier: Programming Language :: Python :: 2
Classifier: Programming Language :: Python :: 2.7
Classifier: Programming Language :: Python :: 3
Classifier: Programming Language :: Python :: 3.4
Classifier: Programming Language :: Python :: 3.5
Classifier: Topic :: Internet :: WWW/HTTP
Classifier: Topic :: Software Development :: Libraries :: Python Modules
Requires-Dist: requests (>=2.4.0)
Requires-Dist: six (>=1.10.0)
Requires-Dist: websocket-client (>=0.22.0)
